covidSumm/__init__.py
covidSumm/abstractive_api.py
covidSumm/abstractive_bart_model.py
covidSumm/abstractive_config.py
covidSumm/abstractive_model.py
covidSumm/abstractive_utils.py
covidSumm/eval_bart_cnn.py
covidSumm/gen_seq_from_trace.py
covidSumm/main.py
covidSumm/s2s_ft/__init__.py
covidSumm/s2s_ft/config.py
covidSumm/s2s_ft/configuration_unilm.py
covidSumm/s2s_ft/convert_state_dict.py
covidSumm/s2s_ft/modeling.py
covidSumm/s2s_ft/modeling_decoding.py
covidSumm/s2s_ft/s2s_loader.py
covidSumm/s2s_ft/tokenization_unilm.py
covidSumm/s2s_ft/utils.py
covidSumm-0.1.5.dist-info/METADATA
covidSumm-0.1.5.dist-info/WHEEL
covidSumm-0.1.5.dist-info/top_level.txt
covidSumm-0.1.5.dist-info/RECORD
