Metadata-Version: 2.1
Name: covidSumm
Version: 0.1.5
Summary: summerization for CORD-19.
Home-page: https://github.com/Iamfinethanksu/covid_summarization
Author: SU Dan
Author-email: sudan0317@gmail.com
License: UNKNOWN
Platform: UNKNOWN
Classifier: Programming Language :: Python :: 3
Classifier: License :: OSI Approved :: MIT License
Classifier: Operating System :: OS Independent
Requires-Python: >=3.6
Requires-Dist: easydict
